MANIFEST.in
README.rst
setup.cfg
setup.py
modisSuite/Compress.py
modisSuite/Downloader.py
modisSuite/__init__.py
modisSuite/clip.py
modisSuite/convert.py
modisSuite/imageObject.py
modisSuite/logMod.py
modisSuite/mosaic.py
modisSuite/subset.py
modisSuite.egg-info/PKG-INFO
modisSuite.egg-info/SOURCES.txt
modisSuite.egg-info/dependency_links.txt
modisSuite.egg-info/requires.txt
modisSuite.egg-info/top_level.txt