Metadata-Version: 1.1
Name: modisSuite
Version: 1.0.0.20
Summary: Python module to download modis data
Home-page: https://github.com/Gabriel-Desharnais/Modis-python-suite
Author: Gabriel Desharnais
Author-email: gabriel.desharnais@hotmail.com
License: MIT
Keywords: modis NSIDC USGS downloader bulk
Platform: UNKNOWN
Classifier: Development Status :: 3 - Alpha
Classifier: Intended Audience :: Science/Research
Classifier: Topic :: Scientific/Engineering :: Atmospheric Science
Classifier: License :: OSI Approved :: MIT License
Classifier: Programming Language :: Python :: 2
Classifier: Programming Language :: Python :: 2.7
Classifier: Programming Language :: Python :: 3
Classifier: Programming Language :: Python :: 3.6
